base_server/__init__.py
base_server/server_async_insecure.py
base_server/server_async_secure.py
base_server/server_sync_insecure.py
base_server/server_sync_secure.py
base_server/mock/__init__.py
base_server/mock/mock_pb2.py
base_server/mock/mock_pb2_grpc.py
digitalkin/__init__.py
digitalkin/__version__.py
digitalkin/logger.py
digitalkin/py.typed
digitalkin/grpc_servers/__init__.py
digitalkin/grpc_servers/_base_server.py
digitalkin/grpc_servers/module_server.py
digitalkin/grpc_servers/module_servicer.py
digitalkin/grpc_servers/registry_server.py
digitalkin/grpc_servers/registry_servicer.py
digitalkin/grpc_servers/utils/exceptions.py
digitalkin/grpc_servers/utils/factory.py
digitalkin/grpc_servers/utils/grpc_client_wrapper.py
digitalkin/grpc_servers/utils/models.py
digitalkin/grpc_servers/utils/types.py
digitalkin/mixins/__init__.py
digitalkin/mixins/base_mixin.py
digitalkin/mixins/callback_mixin.py
digitalkin/mixins/chat_history_mixin.py
digitalkin/mixins/cost_mixin.py
digitalkin/mixins/file_history_mixin.py
digitalkin/mixins/filesystem_mixin.py
digitalkin/mixins/logger_mixin.py
digitalkin/mixins/storage_mixin.py
digitalkin/models/__init__.py
digitalkin/models/module/__init__.py
digitalkin/models/module/module.py
digitalkin/models/module/module_context.py
digitalkin/models/module/module_types.py
digitalkin/models/module/task_monitor.py
digitalkin/models/services/__init__.py
digitalkin/models/services/cost.py
digitalkin/models/services/storage.py
digitalkin/modules/__init__.py
digitalkin/modules/_base_module.py
digitalkin/modules/archetype_module.py
digitalkin/modules/tool_module.py
digitalkin/modules/trigger_handler.py
digitalkin/modules/job_manager/base_job_manager.py
digitalkin/modules/job_manager/job_manager_models.py
digitalkin/modules/job_manager/single_job_manager.py
digitalkin/modules/job_manager/surrealdb_repository.py
digitalkin/modules/job_manager/task_manager.py
digitalkin/modules/job_manager/task_session.py
digitalkin/modules/job_manager/taskiq_broker.py
digitalkin-0.3.0.dist-info/licenses/LICENSE
digitalkin-0.3.0.dist-info/METADATA
digitalkin-0.3.0.dist-info/WHEEL
digitalkin-0.3.0.dist-info/top_level.txt
digitalkin-0.3.0.dist-info/RECORD
