Metadata-Version: 2.4
Name: digitalkin
Version: 0.3.0
Summary: SDK to build kin used in DigitalKin
Author-email: "DigitalKin.ai" <contact@digitalkin.ai>
License: Attribution-NonCommercial-ShareAlike 4.0 International
Project-URL: Homepage, https://github.com/DigitalKin-ai/digitalkin
Project-URL: Documentation, https://github.com/DigitalKin-ai/digitalkin
Project-URL: Issues, https://github.com/DigitalKin-ai/digitalkin/issues
Keywords: digitalkin,kin,agent,gprc,sdk
Classifier: Development Status :: 3 - Alpha
Classifier: Intended Audience :: Developers
Classifier: Operating System :: OS Independent
Classifier: Topic :: Software Development :: Libraries
Classifier: Programming Language :: Python
Classifier: Programming Language :: Python :: 3.10
Classifier: Programming Language :: Python :: 3.11
Classifier: Programming Language :: Python :: 3.12
Classifier: Programming Language :: Python :: 3.13
Classifier: Programming Language :: Python :: 3 :: Only
Classifier: License :: Other/Proprietary License
Requires-Python: >=3.10
License-File: LICENSE
Requires-Dist: digitalkin-proto>=0.1.16
Requires-Dist: grpcio-health-checking>=1.71.0
Requires-Dist: grpcio-reflection>=1.71.0
Requires-Dist: grpcio-status>=1.71.0
Requires-Dist: pydantic>=2.11.10
Requires-Dist: surrealdb>=1.0.6
Provides-Extra: taskiq
Requires-Dist: rstream>=0.31.0; extra == "taskiq"
Requires-Dist: taskiq-aio-pika>=0.4.3; extra == "taskiq"
Requires-Dist: taskiq-redis>=1.1.2; extra == "taskiq"
Requires-Dist: taskiq[reload]>=0.11.18; extra == "taskiq"
Provides-Extra: dev
Requires-Dist: typos>=1.38.0; extra == "dev"
Requires-Dist: ruff>=0.13.3; extra == "dev"
Requires-Dist: mypy>=1.18.2; extra == "dev"
Requires-Dist: pyright>=1.1.406; extra == "dev"
Requires-Dist: pre-commit>=4.3.0; extra == "dev"
Requires-Dist: bump2version>=1.0.1; extra == "dev"
Requires-Dist: build>=1.3.0; extra == "dev"
Requires-Dist: twine>=6.2.0; extra == "dev"
Requires-Dist: cryptography>=46.0.2; extra == "dev"
Provides-Extra: tests
Requires-Dist: freezegun>=1.5.3; extra == "tests"
Requires-Dist: hdrhistogram>=0.10.3; extra == "tests"
Requires-Dist: grpcio-testing>=1.71.0; extra == "tests"
Requires-Dist: psutil>=7.0.0; extra == "tests"
Requires-Dist: pytest>=8.4.2; extra == "tests"
Requires-Dist: pytest-asyncio>=1.2.0; extra == "tests"
Requires-Dist: pytest-cov>=7.0.0; extra == "tests"
Requires-Dist: hypothesis>=6.140.3; extra == "tests"
Dynamic: license-file
